agent.py
agent_profile.py
leonai-0.2.0.dist-info/licenses/LICENSE
middleware/__init__.py
middleware/prompt_caching.py
middleware/search.py
middleware/filesystem/__init__.py
middleware/filesystem/middleware.py
middleware/filesystem/read/__init__.py
middleware/filesystem/read/dispatcher.py
middleware/filesystem/read/types.py
middleware/filesystem/read/readers/__init__.py
middleware/filesystem/read/readers/binary.py
middleware/filesystem/read/readers/notebook.py
middleware/filesystem/read/readers/pdf.py
middleware/filesystem/read/readers/pptx.py
middleware/filesystem/read/readers/text.py
middleware/shell/__init__.py
middleware/shell/executor.py
middleware/shell/hooks/__init__.py
middleware/shell/hooks/base.py
middleware/shell/hooks/command_logger.py
middleware/shell/hooks/dangerous_commands.py
middleware/shell/hooks/file_access_logger.py
middleware/shell/hooks/file_permission.py
middleware/shell/hooks/loader.py
middleware/shell/hooks/path_security.py
middleware/web/__init__.py
middleware/web/middleware.py
middleware/web/types.py
middleware/web/fetchers/__init__.py
middleware/web/fetchers/base.py
middleware/web/fetchers/jina.py
middleware/web/fetchers/markdownify.py
middleware/web/searchers/__init__.py
middleware/web/searchers/base.py
middleware/web/searchers/exa.py
middleware/web/searchers/firecrawl.py
middleware/web/searchers/tavily.py
tui/__init__.py
tui/app.py
tui/config.py
tui/leon_cli.py
tui/session.py
tui/widgets/__init__.py
tui/widgets/chat_input.py
tui/widgets/history_browser.py
tui/widgets/loading.py
tui/widgets/messages.py
tui/widgets/status.py
tui/widgets/thread_browser.py
leonai-0.2.0.dist-info/METADATA
leonai-0.2.0.dist-info/WHEEL
leonai-0.2.0.dist-info/entry_points.txt
leonai-0.2.0.dist-info/top_level.txt
leonai-0.2.0.dist-info/RECORD
