Metadata-Version: 2.4
Name: leonai
Version: 0.2.0
Summary: Leon - Proactive AI coding assistant with persistent memory and TUI
Author: nmhjklnm
License: MIT
Project-URL: Homepage, https://github.com/Ju-Yi-AI-Lab/leonai
Project-URL: Repository, https://github.com/Ju-Yi-AI-Lab/leonai
Project-URL: Issues, https://github.com/Ju-Yi-AI-Lab/leonai/issues
Keywords: ai,assistant,langchain,anthropic,claude,tui,coding
Classifier: Development Status :: 4 - Beta
Classifier: Environment :: Console
Classifier: Intended Audience :: Developers
Classifier: License :: OSI Approved :: MIT License
Classifier: Operating System :: OS Independent
Classifier: Programming Language :: Python :: 3
Classifier: Programming Language :: Python :: 3.12
Classifier: Programming Language :: Python :: 3.13
Classifier: Programming Language :: Python :: 3.14
Classifier: Topic :: Software Development :: Libraries :: Python Modules
Classifier: Topic :: Scientific/Engineering :: Artificial Intelligence
Requires-Python: >=3.12
License-File: LICENSE
Requires-Dist: langchain>=1.2.6
Requires-Dist: langchain-anthropic>=1.3.1
Requires-Dist: langgraph>=1.0.7
Requires-Dist: textual>=1.0.0
Requires-Dist: rich>=13.0.0
Requires-Dist: pyperclip>=1.11.0
Requires-Dist: langchain-openai>=1.1.7
Requires-Dist: duckduckgo-search>=8.1.1
Requires-Dist: httpx>=0.28.1
Requires-Dist: pyyaml>=6.0
Requires-Dist: pydantic>=2.0
Requires-Dist: langchain-mcp-adapters>=0.1.0
Provides-Extra: pdf
Requires-Dist: pymupdf>=1.24.0; extra == "pdf"
Provides-Extra: pptx
Requires-Dist: python-pptx>=1.0.0; extra == "pptx"
Provides-Extra: docs
Requires-Dist: pymupdf>=1.24.0; extra == "docs"
Requires-Dist: python-pptx>=1.0.0; extra == "docs"
Provides-Extra: all
Requires-Dist: pymupdf>=1.24.0; extra == "all"
Requires-Dist: python-pptx>=1.0.0; extra == "all"
Dynamic: license-file
